coinstac_sparse_dinunet
