Metadata-Version: 2.1
Name: coinstac-sparse-dinunet
Version: 2.1.1
Summary: Distributed Sparse Neural Network implementation on COINSTAC.
Home-page: https://github.com/bishalth01/coinstac-sparse-dinunet
Author: Bishal Thapaliya
Author-email: bishalthapaliya16@gmail.com
License: MIT
Classifier: License :: OSI Approved :: MIT License
Classifier: Programming Language :: Python :: 3.6
Classifier: Programming Language :: Python :: 3.7
License-File: LICENSE
